decay_scheme/__init__.py
decay_scheme/data/arrowhead_codes.dat
decay_scheme/data/arrowhead_vertices.dat
decay_scheme/decay_scheme_classes.py
decay_scheme/decay_scheme_drawer.py
decay_scheme-0.0.0a3.dist-info/METADATA
decay_scheme-0.0.0a3.dist-info/WHEEL
decay_scheme-0.0.0a3.dist-info/RECORD
