Metadata-Version: 2.1
Name: decay-scheme
Version: 0.0.0a3
Summary: A python package to draw nuclear decay schemas
Author: Erik Asbjørn Mikkelsen Jensen
Author-email: ej@phys.au.dk
Requires-Python: >=3.8,<4.0
Classifier: Programming Language :: Python :: 3
Classifier: Programming Language :: Python :: 3.8
Classifier: Programming Language :: Python :: 3.9
Classifier: Programming Language :: Python :: 3.10
Classifier: Programming Language :: Python :: 3.11
Requires-Dist: matplotlib (>=3.7.1,<4.0.0)
Requires-Dist: numpy (>=1.24.3,<2.0.0)
